talkscriber/__init__.py
talkscriber/stt/__init__.py
talkscriber/stt/cli.py
talkscriber/stt/client.py
talkscriber/tts/__init__.py
talkscriber/tts/cli.py
talkscriber/tts/client.py
tsclient-1.0.1.dist-info/LICENSE.md
tsclient-1.0.1.dist-info/METADATA
tsclient-1.0.1.dist-info/WHEEL
tsclient-1.0.1.dist-info/entry_points.txt
tsclient-1.0.1.dist-info/top_level.txt
tsclient-1.0.1.dist-info/RECORD
