Metadata-Version: 2.1
Name: tsclient
Version: 1.0.1
Summary: Python client library for Talkscriber Live Transcription and Text-to-Speech services
Home-page: https://github.com/Talkscriber/ts-client
Author: Talkscriber
Author-email: Talkscriber <support@talkscriber.com>
Maintainer-email: Talkscriber <support@talkscriber.com>
License: MIT License
Project-URL: Homepage, https://talkscriber.com
Project-URL: Documentation, https://docs.talkscriber.com
Project-URL: Repository, https://github.com/Talkscriber/ts-client
Project-URL: Bug Tracker, https://github.com/Talkscriber/ts-client/issues
Project-URL: Dashboard, https://app.talkscriber.com
Keywords: talkscriber,speech-to-text,text-to-speech,transcription,tts,stt,websocket,real-time,audio,speech
Classifier: Development Status :: 4 - Beta
Classifier: Intended Audience :: Developers
Classifier: License :: OSI Approved :: MIT License
Classifier: Operating System :: OS Independent
Classifier: Programming Language :: Python :: 3
Classifier: Programming Language :: Python :: 3.8
Classifier: Programming Language :: Python :: 3.9
Classifier: Programming Language :: Python :: 3.10
Classifier: Programming Language :: Python :: 3.11
Classifier: Programming Language :: Python :: 3.12
Classifier: Topic :: Multimedia :: Sound/Audio :: Speech
Classifier: Topic :: Software Development :: Libraries :: Python Modules
Classifier: Topic :: Communications
Requires-Python: >=3.8
License-File: LICENSE.md
Requires-Dist: numpy>=1.21.0
Requires-Dist: scipy>=1.7.0
Requires-Dist: ffmpeg-python>=0.2.0
Requires-Dist: PyAudio>=0.2.11
Requires-Dist: websocket-client>=1.6.0
Requires-Dist: websockets>=11.0.0
Requires-Dist: loguru>=0.7.0
Provides-Extra: dev
Requires-Dist: pytest>=6.0; extra == "dev"
Requires-Dist: pytest-asyncio; extra == "dev"
Requires-Dist: black; extra == "dev"
Requires-Dist: flake8; extra == "dev"
Requires-Dist: mypy; extra == "dev"
Provides-Extra: docs
Requires-Dist: sphinx; extra == "docs"
Requires-Dist: sphinx-rtd-theme; extra == "docs"
